MANIFEST.in
README.rst
REQUIREMENTS
setup.py
patriotwsgi/__init__.py
patriotwsgi.egg-info/PKG-INFO
patriotwsgi.egg-info/SOURCES.txt
patriotwsgi.egg-info/dependency_links.txt
patriotwsgi.egg-info/top_level.txt