Metadata-Version: 1.1
Name: patriotwsgi
Version: 0.0.1
Summary: UNKNOWN
Home-page: https://github.com/nsa-/patriotwsgi
Author: NSA
Author-email: developers@nsa.gov
License: NSL - National Security License
Platform: UNKNOWN
Classifier: Development Status :: 3 - Alpha
Classifier: Programming Language :: Python
Classifier: License :: Free To Use But Restricted
